{
	"name": "IncrementalLoad",
	"properties": {
		"activities": [
			{
				"name": "Lookup1",
				"type": "Lookup",
				"dependsOn": [],
				"policy": {
					"timeout": "7.00:00:00",
					"retry": 0,
					"retryIntervalInSeconds": 30,
					"secureOutput": false,
					"secureInput": false
				},
				"userProperties": [],
				"typeProperties": {
					"source": {
						"type": "AzureSqlSource",
						"sqlReaderQuery": " declare @LastRecord datetime \n\nexec [dbo].[GetHighwaterForLandingEmployeeFromAdventureWorks]  @LastRecordChange = @LastRecord output\n\n  select @LastRecord as LastRecordChange",
						"queryTimeout": "02:00:00",
						"partitionOption": "None"
					},
					"dataset": {
						"referenceName": "AdventureWorks",
						"type": "DatasetReference"
					}
				}
			},
			{
				"name": "Set variable1",
				"type": "SetVariable",
				"dependsOn": [
					{
						"activity": "Lookup1",
						"dependencyConditions": [
							"Succeeded"
						]
					}
				],
				"userProperties": [],
				"typeProperties": {
					"variableName": "LastRecordChange",
					"value": "@activity('Lookup1').output.firstRow.LastRecordChange"
				}
			},
			{
				"name": "Copy data1",
				"type": "Copy",
				"dependsOn": [
					{
						"activity": "Set variable1",
						"dependencyConditions": [
							"Succeeded"
						]
					}
				],
				"policy": {
					"timeout": "7.00:00:00",
					"retry": 0,
					"retryIntervalInSeconds": 30,
					"secureOutput": false,
					"secureInput": false
				},
				"userProperties": [],
				"typeProperties": {
					"source": {
						"type": "AzureSqlSource",
						"sqlReaderQuery": {
							"value": "select * from [HumanResources].[Employee]\n\nwhere ModifiedDate >= '@{variables('LastRecordChange')}'",
							"type": "Expression"
						},
						"queryTimeout": "02:00:00",
						"partitionOption": "None"
					},
					"sink": {
						"type": "AzureSqlSink",
						"preCopyScript": "truncate table dbo.Employee",
						"writeBehavior": "insert",
						"disableMetricsCollection": false
					},
					"enableStaging": false,
					"translator": {
						"type": "TabularTranslator",
						"mappings": [
							{
								"source": {
									"name": "BusinessEntityID",
									"type": "Int32",
									"physicalType": "int"
								},
								"sink": {
									"name": "BusinessEntityID",
									"type": "Int32",
									"physicalType": "int"
								}
							},
							{
								"source": {
									"name": "NationalIDNumber",
									"type": "String",
									"physicalType": "nvarchar"
								},
								"sink": {
									"name": "NationalIDNumber",
									"type": "String",
									"physicalType": "nvarchar"
								}
							},
							{
								"source": {
									"name": "LoginID",
									"type": "String",
									"physicalType": "nvarchar"
								},
								"sink": {
									"name": "LoginID",
									"type": "String",
									"physicalType": "nvarchar"
								}
							},
							{
								"source": {
									"name": "OrganizationNode",
									"physicalType": "hierarchyid"
								},
								"sink": {
									"name": "OrganizationNode",
									"type": "String",
									"physicalType": "nvarchar"
								}
							},
							{
								"source": {
									"name": "OrganizationLevel",
									"type": "Int16",
									"physicalType": "smallint"
								},
								"sink": {
									"name": "OrganizationLevel",
									"type": "String",
									"physicalType": "nvarchar"
								}
							},
							{
								"source": {
									"name": "JobTitle",
									"type": "String",
									"physicalType": "nvarchar"
								},
								"sink": {
									"name": "JobTitle",
									"type": "String",
									"physicalType": "nvarchar"
								}
							},
							{
								"source": {
									"name": "BirthDate",
									"type": "DateTime",
									"physicalType": "date"
								},
								"sink": {
									"name": "BirthDate",
									"type": "DateTime",
									"physicalType": "date"
								}
							},
							{
								"source": {
									"name": "MaritalStatus",
									"type": "String",
									"physicalType": "nchar"
								},
								"sink": {
									"name": "MaritalStatus",
									"type": "String",
									"physicalType": "nchar"
								}
							},
							{
								"source": {
									"name": "Gender",
									"type": "String",
									"physicalType": "nchar"
								},
								"sink": {
									"name": "Gender",
									"type": "String",
									"physicalType": "nchar"
								}
							},
							{
								"source": {
									"name": "HireDate",
									"type": "DateTime",
									"physicalType": "date"
								},
								"sink": {
									"name": "HireDate",
									"type": "DateTime",
									"physicalType": "date"
								}
							},
							{
								"source": {
									"name": "SalariedFlag",
									"type": "Boolean",
									"physicalType": "bit"
								},
								"sink": {
									"name": "SalariedFlag",
									"type": "Boolean",
									"physicalType": "bit"
								}
							},
							{
								"source": {
									"name": "VacationHours",
									"type": "Int16",
									"physicalType": "smallint"
								},
								"sink": {
									"name": "VacationHours",
									"type": "Int16",
									"physicalType": "smallint"
								}
							},
							{
								"source": {
									"name": "SickLeaveHours",
									"type": "Int16",
									"physicalType": "smallint"
								},
								"sink": {
									"name": "SickLeaveHours",
									"type": "Int16",
									"physicalType": "smallint"
								}
							},
							{
								"source": {
									"name": "CurrentFlag",
									"type": "Boolean",
									"physicalType": "bit"
								},
								"sink": {
									"name": "CurrentFlag",
									"type": "Boolean",
									"physicalType": "bit"
								}
							},
							{
								"source": {
									"name": "ModifiedDate",
									"type": "DateTime",
									"physicalType": "datetime"
								},
								"sink": {
									"name": "ModifiedDate",
									"type": "DateTime",
									"physicalType": "datetime"
								}
							}
						],
						"typeConversion": true,
						"typeConversionSettings": {
							"allowDataTruncation": true,
							"treatBooleanAsNumber": false
						}
					}
				},
				"inputs": [
					{
						"referenceName": "AdventureWorks",
						"type": "DatasetReference"
					}
				],
				"outputs": [
					{
						"referenceName": "AdventureWorksEmployee",
						"type": "DatasetReference"
					}
				]
			},
			{
				"name": "Stored procedure1",
				"type": "SqlServerStoredProcedure",
				"dependsOn": [
					{
						"activity": "Copy data1",
						"dependencyConditions": [
							"Succeeded"
						]
					}
				],
				"policy": {
					"timeout": "7.00:00:00",
					"retry": 0,
					"retryIntervalInSeconds": 30,
					"secureOutput": false,
					"secureInput": false
				},
				"userProperties": [],
				"typeProperties": {
					"storedProcedureName": "[dbo].[UpdateHighWater]",
					"storedProcedureParameters": {
						"TableName": {
							"value": "dbo.Employee",
							"type": "String"
						}
					}
				},
				"linkedServiceName": {
					"referenceName": "AdventureWorks",
					"type": "LinkedServiceReference"
				}
			}
		],
		"variables": {
			"LastRecordChange": {
				"type": "String"
			}
		},
		"annotations": []
	}
}